virtualpdu/__init__.py
virtualpdu/core.py
virtualpdu/main.py
virtualpdu/drivers/__init__.py
virtualpdu/drivers/libvirt_driver.py
virtualpdu/pdu/__init__.py
virtualpdu/pdu/apc_rackpdu.py
virtualpdu/pdu/baytech_mrp27.py
virtualpdu/pdu/pysnmp_handler.py
virtualpdu/tests/__init__.py
virtualpdu/tests/base.py
virtualpdu/tests/snmp_client.py
virtualpdu/tests/snmp_error_indications.py
virtualpdu/tests/integration/__init__.py
virtualpdu/tests/integration/test_core_integration.py
virtualpdu/tests/integration/test_entrypoint.py
virtualpdu/tests/integration/drivers/__init__.py
virtualpdu/tests/integration/drivers/test_libvirt_driver.py
virtualpdu/tests/integration/pdu/__init__.py
virtualpdu/tests/integration/pdu/test_apc_rackpdu.py
virtualpdu/tests/integration/pdu/test_baytech_mrp27.py
virtualpdu/tests/integration/pdu/test_pdu.py
virtualpdu/tests/integration/pdu/test_pysnmp_handler.py
virtualpdu/tests/unit/__init__.py
virtualpdu/tests/unit/test_core.py
virtualpdu/tests/unit/test_main.py
virtualpdu/tests/unit/test_pysnmp_handler.py
virtualpdu/tests/unit/test_snmp_client.py
virtualpdu/tests/unit/test_transitive_state.py
virtualpdu/tests/unit/drivers/__init__.py
virtualpdu/tests/unit/drivers/test_driver.py
virtualpdu/tests/unit/drivers/test_libvirt_driver.py
virtualpdu/tests/unit/pdu/__init__.py
virtualpdu/tests/unit/pdu/base_pdu_test_cases.py
virtualpdu/tests/unit/pdu/test_apc_rackpdu.py
virtualpdu/tests/unit/pdu/test_base_pdu.py
virtualpdu/tests/unit/pdu/test_baytech_mrp27.py
virtualpdu-2.2.0.dist-info/AUTHORS
virtualpdu-2.2.0.dist-info/LICENSE
virtualpdu-2.2.0.dist-info/METADATA
virtualpdu-2.2.0.dist-info/WHEEL
virtualpdu-2.2.0.dist-info/entry_points.txt
virtualpdu-2.2.0.dist-info/pbr.json
virtualpdu-2.2.0.dist-info/top_level.txt
virtualpdu-2.2.0.dist-info/RECORD
